odoo/addons/mrp_bom_equivalent/README.rst
odoo/addons/mrp_bom_equivalent/__init__.py
odoo/addons/mrp_bom_equivalent/__manifest__.py
odoo/addons/mrp_bom_equivalent/models/__init__.py
odoo/addons/mrp_bom_equivalent/models/mrp.py
odoo/addons/mrp_bom_equivalent/models/product.py
odoo/addons/mrp_bom_equivalent/static/description/icon.png
odoo/addons/mrp_bom_equivalent/views/mrp_view.xml
odoo11_addon_mrp_bom_equivalent-11.0.1.0.0.dist-info/DESCRIPTION.rst
odoo11_addon_mrp_bom_equivalent-11.0.1.0.0.dist-info/METADATA
odoo11_addon_mrp_bom_equivalent-11.0.1.0.0.dist-info/RECORD
odoo11_addon_mrp_bom_equivalent-11.0.1.0.0.dist-info/WHEEL
odoo11_addon_mrp_bom_equivalent-11.0.1.0.0.dist-info/metadata.json
odoo11_addon_mrp_bom_equivalent-11.0.1.0.0.dist-info/top_level.txt
